<?xml version="1.0" encoding="UTF-8"?>
<ledger>
  <categories>
    <category>Groceries</category>
    <category>Dining</category>
    <category>Utilities</category>
    <category>Rent/Mortgage</category>
    <category>Travel</category>
    <category>Entertainment</category>
    <category>Subscriptions</category>
    <category>Medical</category>
    <category>Shopping</category>
    <category>Transportation</category>
    <category>Income</category>
    <category>Transfer</category>
    <category>Credit Card Payment (EMI)</category>
    <category>Other</category>
  </categories>
  <cards>
    <card id="mrxjugou1rp8ct">
      <name>Amex</name>
      <limit>18000</limit>
      <due>2026-07-10</due>
      <apr></apr>
    </card>
    <card id="mrxjv1nb2sm2fo">
      <name>Bofa-7119</name>
      <limit>26000</limit>
      <due></due>
      <apr></apr>
    </card>
    <card id="mrxjw32e833m7v">
      <name>Bofa-3373</name>
      <limit>2000</limit>
      <due></due>
      <apr></apr>
    </card>
    <card id="mrxjwpwps87hd6">
      <name>City</name>
      <limit>6000</limit>
      <due></due>
      <apr></apr>
    </card>
    <card id="mrxjzdd2uqc34l">
      <name>CapitalOne</name>
      <limit>2000</limit>
      <due></due>
      <apr></apr>
    </card>
    <card id="mrxk12jbaug7we">
      <name>Chase-Freedom</name>
      <limit>6400</limit>
      <due></due>
      <apr></apr>
    </card>
    <card id="mrxk1ov2bsmgcq">
      <name>Chase-Amazon</name>
      <limit>9100</limit>
      <due></due>
      <apr></apr>
    </card>
    <card id="mrxk26nnvjdy5d">
      <name>Chase-Slate</name>
      <limit>6800</limit>
      <due></due>
      <apr></apr>
    </card>
    <card id="mrxk677jycb6ka">
      <name>Discover</name>
      <limit>6000</limit>
      <due></due>
      <apr></apr>
    </card>
  </cards>
  <accounts>
    <account id="mrxk6yzm83jsfp">
      <name>Bofa-Checking</name>
      <start>4142</start>
    </account>
    <account id="mrxk7tnsc5zh1i">
      <name>DCU-Checking</name>
      <start>1005.56</start>
    </account>
    <account id="mrxk88ibgenzqw">
      <name>DCU-Saving</name>
      <start>267.11</start>
    </account>
  </accounts>
  <expenses>

  </expenses>
  <transactions>

  </transactions>
</ledger>